Workbook

Sheet Instructions
A1: Interest Budget Model – Placements & Government Deposits
A2: Budget horizon: Q4 2026 and FY 2027 (quarterly). Amounts in millions of local currency.
A4: HOW THE MODEL WORKS
A5: 1. Assumptions: set the day-count basis, the benchmark rate path per quarter (e.g., EIBOR / SOFR / policy rate) and an optional rate shock.
A6: 2. Placements (asset side): list each bank counterparty, its opening balance at 30-Sep-2026, rate type (Fixed/Floating), fixed rate or spread, and the planned net change in balance each quarter.
A7: 3. Govt Deposits (liability side): same structure for Ministry of Finance / government entity deposits. Spreads can be negative (deposits priced below benchmark).
A8: 4. The model computes closing balance -> average balance -> effective rate -> interest = Average balance x Rate x Days / Day-count basis.
A9: 5. Summary: quarterly interest income, interest expense, net interest, yields/costs, totals for Q4-2026 and FY-2027, plus a +100bp sensitivity.
A11: LEGEND
A12: Blue text = hardcoded input (edit these)
A13: Black text = formula (do not edit)
A14: Green text = link from another sheet
... A21: • Average balance = simple average of opening and closing balance for the quarter (assumes balance changes evenly through the quarter).

Sheet Summary
A1: Budget Summary – Interest on Placements & Government Deposits
A2: Amounts in millions of local currency.
A4: Line item | F4: =Assumptions!F$10 -> Q4-2026 | G4: =Assumptions!G$10 -> Q1-2027 | H4: =Assumptions!H$10 -> Q2-2027 | I4: =Assumptions!I$10 -> Q3-2027 | J4: =Assumptions!J$10 -> Q4-2027 | K4: FY-2027 | L4: Q4-26 + FY-27
A5: Placements with banks
A6: Average balance | F6: =Placements!F27 -> 1000 | G6: =Placements!G27 -> 962.5 | H6: =Placements!H27 -> 950 | I6: =Placements!I27 -> 975 | J6: =Placements!J27 -> 987.5 | K6: =Placements!K27 -> 968.83562
A7: Interest income | F7: =Placements!F43 -> 10.343611 | G7: =Placements!G43 -> 9.484375 | H7: =Placements!H43 -> 9.1347569 | I7: =Placements!I43 -> 9.2670833 | J7: =Placements!J43 -> 9.386875 | K7: =Placements!K43 -> 37.27309 | L7: =F7+K7 -> 47.616701
A8: Average yield | F8: =Placements!F35 -> 0.040475 | G8: =Placements!G35 -> 0.039415584 | H8: =Placements!H35 -> 0.038039474 | I8: =Placements!I35 -> 0.037192308 | J8: =Placements!J35 -> 0.037196203 | K8: =Placements!K35 -> 0.037945034
A10: Government deposits
A11: Average balance | F11: ='Govt Deposits'!F27 -> 1900 | G11: ='Govt Deposits'!G27 -> 1950 | H11: ='Govt Deposits'!H27 -> 1850 | I11: ='Govt Deposits'!I27 -> 1775 | J11: ='Govt Deposits'!J27 -> 1800 | K11: ='Govt Deposits'!K27 -> 1843.1507
A12: Interest expense | F12: ='Govt Deposits'!F43 -> 16.349167 | G12: ='Govt Deposits'!G43 -> 16.1875 | H12: ='Govt Deposits'!H43 -> 15.116111 | I12: ='Govt Deposits'!I43 -> 14.314306 | J12: ='Govt Deposits'!J43 -> 14.521944 | K12: ='Govt Deposits'!K43 -> 60.139861 | L12: =F12+K12 -> 76.489028
A13: Average cost | F13: ='Govt Deposits'!F35 -> 0.033671053 | G13: ='Govt Deposits'!G35 -> 0.033205128 | H13: ='Govt Deposits'!H35 -> 0.032324324 | I13: ='Govt Deposits'!I35 -> 0.031556338 | J13: ='Govt Deposits'!J35 -> 0.031569444 | K13: ='Govt Deposits'!K35 -> 0.032181865
A15: Net interest contribution
A16: Interest income – interest expense | F16: =F7-F12 -> -6.0055556 | G16: =G7-G12 -> -6.703125 | H16: =H7-H12 -> -5.9813542 | I16: =I7-I12 -> -5.0472222 | J16: =J7-J12 -> -5.1350694 | K16: =K7-K12 -> -22.866771 | L16: =L7-L12 -> -28.872326
A17: Spread (yield – cost) | F17: =F8-F13 -> 0.0068039474 | G17: =G8-G13 -> 0.0062104562 | H17: =H8-H13 -> 0.0057151494 | I17: =I8-I13 -> 0.0056359697 | J17: =J8-J13 -> 0.0056267581 | K17: =K8-K13 -> 0.0057631681
A18: Funding gap (placements – govt deposits avg bal.) | F18: =F6-F11 -> -900 | G18: =G6-G11 -> -987.5 | H18: =H6-H11 -> -900 | I18: =I6-I11 -> -800 | J18: =J6-J11 -> -812.5 | K18: =K6-K11 -> -874.31507
A20: Sensitivity: parallel rate move on Floating lines
A21: Rate move (bp, decimal) | E21: 0.01
A22: Change in interest income (floating placements) | F22: =SUMIF(Placements!$B$6:$B$10,"Floating",Placements!F$22:F$26)*$E$21*Assumptions!F$13/Assumptions!$E$5 -> 1.7888889 | G22: =SUMIF(Placements!$B$6:$B$10,"Floating",Placements!G$22:G$26)*$E$21*Assumptions!G$13/Assumptions!$E$5 -> 1.78125 | H22: =SUMIF(Placements!$B$6:$B$10,"Floating",Placements!H$22:H$26)*$E$21*Assumptions!H$13/Assumptions!$E$5 -> 1.8958333 | I22: =SUMIF(Placements!$B$6:$B$10,"Floating",Placements!I$22:I$26)*$E$21*Assumptions!I$13/Assumptions!$E$5 -> 1.9805556 | J22: =SUMIF(Placements!$B$6:$B$10,"Floating",Placements!J$22:J$26)*$E$21*Assumptions!J$13/Assumptions!$E$5 -> 2.0125 | K22: =SUM(G22:J22) -> 7.6701389 | L22: =F22+K22 -> 9.4590278
A23: Change in interest expense (floating govt deposits) | F23: =SUMIF('Govt Deposits'!$B$6:$B$10,"Floating",'Govt Deposits'!F$22:F$26)*$E$21*Assumptions!F$13/Assumptions!$E$5 -> 1.6611111 | G23: =SUMIF('Govt Deposits'!$B$6:$B$10,"Floating",'Govt Deposits'!G$22:G$26)*$E$21*Assumptions!G$13/Assumptions!$E$5 -> 1.75 | H23: =SUMIF('Govt Deposits'!$B$6:$B$10,"Floating",'Govt Deposits'!H$22:H$26)*$E$21*Assumptions!H$13/Assumptions!$E$5 -> 1.7694444 | I23: =SUMIF('Govt Deposits'!$B$6:$B$10,"Floating",'Govt Deposits'!I$22:I$26)*$E$21*Assumptions!I$13/Assumptions!$E$5 -> 1.8527778 | J23: =SUMIF('Govt Deposits'!$B$6:$B$10,"Floating",'Govt Deposits'!J$22:J$26)*$E$21*Assumptions!J$13/Assumptions!$E$5 -> 1.9166667 | K23: =SUM(G23:J23) -> 7.2888889 | L23: =F23+K23 -> 8.95
A24: Change in net interest | F24: =F22-F23 -> 0.12777778 | G24: =G22-G23 -> 0.03125 | H24: =H22-H23 -> 0.12638889 | I24: =I22-I23 -> 0.12777778 | J24: =J22-J23 -> 0.095833333 | K24: =SUM(G24:J24) -> 0.38125 | L24: =F24+K24 -> 0.50902778
A26: Q4-2026 = column F; FY-2027 = sum of Q1–Q4 2027. Change the Assumptions sheet (benchmark path, shock) to run scenarios.

Sheet Assumptions
A1: Assumptions
A2: Rates stored as decimals (3.90% = 0.039).
A4: General
A5: Day-count basis (days) | E5: 360
A6: Rate shock on Floating lines (bp, decimal) | E6: 0
A7: Opening balance date | E7: 46295
A9: Quarterly periods
A10: Period | F10: Q4-2026 | G10: Q1-2027 | H10: Q2-2027 | I10: Q3-2027 | J10: Q4-2027
A11: Start date | F11: 46296 | G11: 46388 | H11: 46478 | I11: 46569 | J11: 46661
A12: End date | F12: 46387 | G12: 46477 | H12: 46568 | I12: 46660 | J12: 46752
A13: Days in period | F13: =F12-F11+1 -> 92 | G13: =G12-G11+1 -> 90 | H13: =H12-H11+1 -> 91 | I13: =I12-I11+1 -> 92 | J13: =J12-J11+1 -> 92
A14: Benchmark rate (e.g., 3M EIBOR / SOFR) | F14: 0.039 | G14: 0.0375 | H14: 0.036 | I14: 0.035 | J14: 0.035
A15: Source: illustrative placeholder path – replace with Treasury/ALCO house view or market forward curve.

Sheet Placements
A1: Interest Income – Placements with Other Banks
A2: Amounts in millions of local currency. Rates as decimals.
A4: 1. Inputs – counterparty terms and planned net change in balance
A5: Counterparty | B5: Rate type | C5: Fixed rate | D5: Spread vs benchmark | E5: Opening bal. 30-Sep-26 | F5: =Assumptions!F$10 -> Q4-2026 | G5: =Assumptions!G$10 -> Q1-2027 | H5: =Assumptions!H$10 -> Q2-2027 | I5: =Assumptions!I$10 -> Q3-2027 | J5: =Assumptions!J$10 -> Q4-2027 | K5: FY-2027
A6: Bank A – 3M term placement | B6: Floating | C6: 0 | D6: 0.0025 | E6: 500 | F6: 50 | G6: 0 | H6: 25 | I6: 0 | J6: 25 | K6: =SUM(G6:J6) -> 50
A7: Bank B – 6M fixed placement | B7: Fixed | C7: 0.041 | D7: 0 | E7: 300 | F7: 0 | G7: -100 | H7: 0 | I7: 0 | J7: 0 | K7: =SUM(G7:J7) -> -100
A8: Bank C – call / overnight | B8: Floating | C8: 0 | D8: -0.0025 | E8: 200 | F8: -50 | G8: 25 | H8: 25 | I8: 0 | J8: 0 | K8: =SUM(G8:J8) -> 50
A9: Counterparty 4 | B9: Floating | C9: 0 | D9: 0 | E9: 0 | F9: 0 | G9: 0 | H9: 0 | I9: 0 | J9: 0 | K9: =SUM(G9:J9) -> 0
A10: Counterparty 5 | B10: Floating | C10: 0 | D10: 0 | E10: 0 | F10: 0 | G10: 0 | H10: 0 | I10: 0 | J10: 0 | K10: =SUM(G10:J10) -> 0
A11: Total | E11: =SUM(E6:E10) -> 1000 | F11: =SUM(F6:F10) -> 0 | G11: =SUM(G6:G10) -> -75 | H11: =SUM(H6:H10) -> 50 | I11: =SUM(I6:I10) -> 0 | J11: =SUM(J6:J10) -> 25 | K11: =SUM(K6:K10) -> 0
A13: 2. Closing balance | F13: =Assumptions!F$10 -> Q4-2026 | G13: =Assumptions!G$10 -> Q1-2027 | H13: =Assumptions!H$10 -> Q2-2027 | I13: =Assumptions!I$10 -> Q3-2027 | J13: =Assumptions!J$10 -> Q4-2027 | K13: Year-end
A14: =A6 -> Bank A – 3M term placement | F14: =$E6+F6 -> 550 | G14: =F14+G6 -> 550 | H14: =G14+H6 -> 575 | I14: =H14+I6 -> 575 | J14: =I14+J6 -> 600 | K14: =J14 -> 600
A15: =A7 -> Bank B – 6M fixed placement | F15: =$E7+F7 -> 300 | G15: =F15+G7 -> 200 | H15: =G15+H7 -> 200 | I15: =H15+I7 -> 200 | J15: =I15+J7 -> 200 | K15: =J15 -> 200
A16: =A8 -> Bank C – call / overnight | F16: =$E8+F8 -> 150 | G16: =F16+G8 -> 175 | H16: =G16+H8 -> 200 | I16: =H16+I8 -> 200 | J16: =I16+J8 -> 200 | K16: =J16 -> 200
A17: =A9 -> Counterparty 4 | F17: =$E9+F9 -> 0 | G17: =F17+G9 -> 0 | H17: =G17+H9 -> 0 | I17: =H17+I9 -> 0 | J17: =I17+J9 -> 0 | K17: =J17 -> 0
A18: =A10 -> Counterparty 5 | F18: =$E10+F10 -> 0 | G18: =F18+G10 -> 0 | H18: =G18+H10 -> 0 | I18: =H18+I10 -> 0 | J18: =I18+J10 -> 0 | K18: =J18 -> 0
A19: Total closing balance | F19: =SUM(F14:F18) -> 1000 | G19: =SUM(G14:G18) -> 925 | H19: =SUM(H14:H18) -> 975 | I19: =SUM(I14:I18) -> 975 | J19: =SUM(J14:J18) -> 1000 | K19: =SUM(K14:K18) -> 1000
A21: 3. Average balance for the quarter | F21: =Assumptions!F$10 -> Q4-2026 | G21: =Assumptions!G$10 -> Q1-2027 | H21: =Assumptions!H$10 -> Q2-2027 | I21: =Assumptions!I$10 -> Q3-2027 | J21: =Assumptions!J$10 -> Q4-2027 | K21: FY-2027 avg
A22: =A6 -> Bank A – 3M term placement | F22: =($E6+F14)/2 -> 525 | G22: =(F14+G14)/2 -> 550 | H22: =(G14+H14)/2 -> 562.5 | I22: =(H14+I14)/2 -> 575 | J22: =(I14+J14)/2 -> 587.5 | K22: =SUMPRODUCT(G22:J22,Assumptions!$G$13:$J$13)/SUM(Assumptions!$G$13:$J$13) -> 568.86986
A23: =A7 -> Bank B – 6M fixed placement | F23: =($E7+F15)/2 -> 300 | G23: =(F15+G15)/2 -> 250 | H23: =(G15+H15)/2 -> 200 | I23: =(H15+I15)/2 -> 200 | J23: =(I15+J15)/2 -> 200 | K23: =SUMPRODUCT(G23:J23,Assumptions!$G$13:$J$13)/SUM(Assumptions!$G$13:$J$13) -> 212.32877
A24: =A8 -> Bank C – call / overnight | F24: =($E8+F16)/2 -> 175 | G24: =(F16+G16)/2 -> 162.5 | H24: =(G16+H16)/2 -> 187.5 | I24: =(H16+I16)/2 -> 200 | J24: =(I16+J16)/2 -> 200 | K24: =SUMPRODUCT(G24:J24,Assumptions!$G$13:$J$13)/SUM(Assumptions!$G$13:$J$13) -> 187.63699
A25: =A9 -> Counterparty 4 | F25: =($E9+F17)/2 -> 0 | G25: =(F17+G17)/2 -> 0 | H25: =(G17+H17)/2 -> 0 | I25: =(H17+I17)/2 -> 0 | J25: =(I17+J17)/2 -> 0 | K25: =SUMPRODUCT(G25:J25,Assumptions!$G$13:$J$13)/SUM(Assumptions!$G$13:$J$13) -> 0
A26: =A10 -> Counterparty 5 | F26: =($E10+F18)/2 -> 0 | G26: =(F18+G18)/2 -> 0 | H26: =(G18+H18)/2 -> 0 | I26: =(H18+I18)/2 -> 0 | J26: =(I18+J18)/2 -> 0 | K26: =SUMPRODUCT(G26:J26,Assumptions!$G$13:$J$13)/SUM(Assumptions!$G$13:$J$13) -> 0
A27: Total average balance | F27: =SUM(F22:F26) -> 1000 | G27: =SUM(G22:G26) -> 962.5 | H27: =SUM(H22:H26) -> 950 | I27: =SUM(I22:I26) -> 975 | J27: =SUM(J22:J26) -> 987.5 | K27: =SUM(K22:K26) -> 968.83562
A29: 4. Effective interest rate (annualised) | F29: =Assumptions!F$10 -> Q4-2026 | G29: =Assumptions!G$10 -> Q1-2027 | H29: =Assumptions!H$10 -> Q2-2027 | I29: =Assumptions!I$10 -> Q3-2027 | J29: =Assumptions!J$10 -> Q4-2027
A30: =A6 -> Bank A – 3M term placement | F30: =IF($B6="Fixed",$C6,Assumptions!F$14+$D6+Assumptions!$E$6) -> 0.0415 | G30: =IF($B6="Fixed",$C6,Assumptions!G$14+$D6+Assumptions!$E$6) -> 0.04 | H30: =IF($B6="Fixed",$C6,Assumptions!H$14+$D6+Assumptions!$E$6) -> 0.0385 | I30: =IF($B6="Fixed",$C6,Assumptions!I$14+$D6+Assumptions!$E$6) -> 0.0375 | J30: =IF($B6="Fixed",$C6,Assumptions!J$14+$D6+Assumptions!$E$6) -> 0.0375
A31: =A7 -> Bank B – 6M fixed placement | F31: =IF($B7="Fixed",$C7,Assumptions!F$14+$D7+Assumptions!$E$6) -> 0.041 | G31: =IF($B7="Fixed",$C7,Assumptions!G$14+$D7+Assumptions!$E$6) -> 0.041 | H31: =IF($B7="Fixed",$C7,Assumptions!H$14+$D7+Assumptions!$E$6) -> 0.041 | I31: =IF($B7="Fixed",$C7,Assumptions!I$14+$D7+Assumptions!$E$6) -> 0.041 | J31: =IF($B7="Fixed",$C7,Assumptions!J$14+$D7+Assumptions!$E$6) -> 0.041
A32: =A8 -> Bank C – call / overnight | F32: =IF($B8="Fixed",$C8,Assumptions!F$14+$D8+Assumptions!$E$6) -> 0.0365 | G32: =IF($B8="Fixed",$C8,Assumptions!G$14+$D8+Assumptions!$E$6) -> 0.035 | H32: =IF($B8="Fixed",$C8,Assumptions!H$14+$D8+Assumptions!$E$6) -> 0.0335 | I32: =IF($B8="Fixed",$C8,Assumptions!I$14+$D8+Assumptions!$E$6) -> 0.0325 | J32: =IF($B8="Fixed",$C8,Assumptions!J$14+$D8+Assumptions!$E$6) -> 0.0325
A33: =A9 -> Counterparty 4 | F33: =IF($B9="Fixed",$C9,Assumptions!F$14+$D9+Assumptions!$E$6) -> 0.039 | G33: =IF($B9="Fixed",$C9,Assumptions!G$14+$D9+Assumptions!$E$6) -> 0.0375 | H33: =IF($B9="Fixed",$C9,Assumptions!H$14+$D9+Assumptions!$E$6) -> 0.036 | I33: =IF($B9="Fixed",$C9,Assumptions!I$14+$D9+Assumptions!$E$6) -> 0.035 | J33: =IF($B9="Fixed",$C9,Assumptions!J$14+$D9+Assumptions!$E$6) -> 0.035
A34: =A10 -> Counterparty 5 | F34: =IF($B10="Fixed",$C10,Assumptions!F$14+$D10+Assumptions!$E$6) -> 0.039 | G34: =IF($B10="Fixed",$C10,Assumptions!G$14+$D10+Assumptions!$E$6) -> 0.0375 | H34: =IF($B10="Fixed",$C10,Assumptions!H$14+$D10+Assumptions!$E$6) -> 0.036 | I34: =IF($B10="Fixed",$C10,Assumptions!I$14+$D10+Assumptions!$E$6) -> 0.035 | J34: =IF($B10="Fixed",$C10,Assumptions!J$14+$D10+Assumptions!$E$6) -> 0.035
A35: Weighted average rate | F35: =IFERROR(F43/F27*Assumptions!$E$5/Assumptions!F$13,0) -> 0.040475 | G35: =IFERROR(G43/G27*Assumptions!$E$5/Assumptions!G$13,0) -> 0.039415584 | H35: =IFERROR(H43/H27*Assumptions!$E$5/Assumptions!H$13,0) -> 0.038039474 | I35: =IFERROR(I43/I27*Assumptions!$E$5/Assumptions!I$13,0) -> 0.037192308 | J35: =IFERROR(J43/J27*Assumptions!$E$5/Assumptions!J$13,0) -> 0.037196203 | K35: =IFERROR(K43/K27*Assumptions!$E$5/SUM(Assumptions!$G$13:$J$13),0) -> 0.037945034
A37: 5. Interest income | F37: =Assumptions!F$10 -> Q4-2026 | G37: =Assumptions!G$10 -> Q1-2027 | H37: =Assumptions!H$10 -> Q2-2027 | I37: =Assumptions!I$10 -> Q3-2027 | J37: =Assumptions!J$10 -> Q4-2027 | K37: FY-2027
A38: =A6 -> Bank A – 3M term placement | F38: =F22*F30*Assumptions!F$13/Assumptions!$E$5 -> 5.5679167 | G38: =G22*G30*Assumptions!G$13/Assumptions!$E$5 -> 5.5 | H38: =H22*H30*Assumptions!H$13/Assumptions!$E$5 -> 5.4742188 | I38: =I22*I30*Assumptions!I$13/Assumptions!$E$5 -> 5.5104167 | J38: =J22*J30*Assumptions!J$13/Assumptions!$E$5 -> 5.6302083 | K38: =SUM(G38:J38) -> 22.114844
A39: =A7 -> Bank B – 6M fixed placement | F39: =F23*F31*Assumptions!F$13/Assumptions!$E$5 -> 3.1433333 | G39: =G23*G31*Assumptions!G$13/Assumptions!$E$5 -> 2.5625 | H39: =H23*H31*Assumptions!H$13/Assumptions!$E$5 -> 2.0727778 | I39: =I23*I31*Assumptions!I$13/Assumptions!$E$5 -> 2.0955556 | J39: =J23*J31*Assumptions!J$13/Assumptions!$E$5 -> 2.0955556 | K39: =SUM(G39:J39) -> 8.8263889
A40: =A8 -> Bank C – call / overnight | F40: =F24*F32*Assumptions!F$13/Assumptions!$E$5 -> 1.6323611 | G40: =G24*G32*Assumptions!G$13/Assumptions!$E$5 -> 1.421875 | H40: =H24*H32*Assumptions!H$13/Assumptions!$E$5 -> 1.5877604 | I40: =I24*I32*Assumptions!I$13/Assumptions!$E$5 -> 1.6611111 | J40: =J24*J32*Assumptions!J$13/Assumptions!$E$5 -> 1.6611111 | K40: =SUM(G40:J40) -> 6.3318576
A41: =A9 -> Counterparty 4 | F41: =F25*F33*Assumptions!F$13/Assumptions!$E$5 -> 0 | G41: =G25*G33*Assumptions!G$13/Assumptions!$E$5 -> 0 | H41: =H25*H33*Assumptions!H$13/Assumptions!$E$5 -> 0 | I41: =I25*I33*Assumptions!I$13/Assumptions!$E$5 -> 0 | J41: =J25*J33*Assumptions!J$13/Assumptions!$E$5 -> 0 | K41: =SUM(G41:J41) -> 0
A42: =A10 -> Counterparty 5 | F42: =F26*F34*Assumptions!F$13/Assumptions!$E$5 -> 0 | G42: =G26*G34*Assumptions!G$13/Assumptions!$E$5 -> 0 | H42: =H26*H34*Assumptions!H$13/Assumptions!$E$5 -> 0 | I42: =I26*I34*Assumptions!I$13/Assumptions!$E$5 -> 0 | J42: =J26*J34*Assumptions!J$13/Assumptions!$E$5 -> 0 | K42: =SUM(G42:J42) -> 0
A43: Total interest income | F43: =SUM(F38:F42) -> 10.343611 | G43: =SUM(G38:G42) -> 9.484375 | H43: =SUM(H38:H42) -> 9.1347569 | I43: =SUM(I38:I42) -> 9.2670833 | J43: =SUM(J38:J42) -> 9.386875 | K43: =SUM(K38:K42) -> 37.27309

Sheet Govt Deposits
A1: Interest Expense – Government Deposits
A2: Amounts in millions of local currency. Rates as decimals.
A4: 1. Inputs – counterparty terms and planned net change in balance
A5: Counterparty | B5: Rate type | C5: Fixed rate | D5: Spread vs benchmark | E5: Opening bal. 30-Sep-26 | F5: =Assumptions!F$10 -> Q4-2026 | G5: =Assumptions!G$10 -> Q1-2027 | H5: =Assumptions!H$10 -> Q2-2027 | I5: =Assumptions!I$10 -> Q3-2027 | J5: =Assumptions!J$10 -> Q4-2027 | K5: FY-2027
A6: Ministry of Finance – term deposit | B6: Fixed | C6: 0.039 | D6: 0 | E6: 1000 | F6: 0 | G6: 0 | H6: -200 | I6: 0 | J6: 0 | K6: =SUM(G6:J6) -> -200
A7: Govt entity X – floating deposit | B7: Floating | C7: 0 | D7: -0.0025 | E7: 600 | F7: 100 | G7: 0 | H7: 0 | I7: 50 | J7: 0 | K7: =SUM(G7:J7) -> 50
A8: Govt-related entity – call account | B8: Fixed | C8: 0.005 | D8: 0 | E8: 250 | F8: 0 | G8: 0 | H8: 0 | I8: 0 | J8: 0 | K8: =SUM(G8:J8) -> 0
A9: Depositor 4 | B9: Floating | C9: 0 | D9: 0 | E9: 0 | F9: 0 | G9: 0 | H9: 0 | I9: 0 | J9: 0 | K9: =SUM(G9:J9) -> 0
A10: Depositor 5 | B10: Floating | C10: 0 | D10: 0 | E10: 0 | F10: 0 | G10: 0 | H10: 0 | I10: 0 | J10: 0 | K10: =SUM(G10:J10) -> 0
A11: Total | E11: =SUM(E6:E10) -> 1850 | F11: =SUM(F6:F10) -> 100 | G11: =SUM(G6:G10) -> 0 | H11: =SUM(H6:H10) -> -200 | I11: =SUM(I6:I10) -> 50 | J11: =SUM(J6:J10) -> 0 | K11: =SUM(K6:K10) -> -150
A13: 2. Closing balance | F13: =Assumptions!F$10 -> Q4-2026 | G13: =Assumptions!G$10 -> Q1-2027 | H13: =Assumptions!H$10 -> Q2-2027 | I13: =Assumptions!I$10 -> Q3-2027 | J13: =Assumptions!J$10 -> Q4-2027 | K13: Year-end
A14: =A6 -> Ministry of Finance – term deposit | F14: =$E6+F6 -> 1000 | G14: =F14+G6 -> 1000 | H14: =G14+H6 -> 800 | I14: =H14+I6 -> 800 | J14: =I14+J6 -> 800 | K14: =J14 -> 800
A15: =A7 -> Govt entity X – floating deposit | F15: =$E7+F7 -> 700 | G15: =F15+G7 -> 700 | H15: =G15+H7 -> 700 | I15: =H15+I7 -> 750 | J15: =I15+J7 -> 750 | K15: =J15 -> 750
A16: =A8 -> Govt-related entity – call account | F16: =$E8+F8 -> 250 | G16: =F16+G8 -> 250 | H16: =G16+H8 -> 250 | I16: =H16+I8 -> 250 | J16: =I16+J8 -> 250 | K16: =J16 -> 250
A17: =A9 -> Depositor 4 | F17: =$E9+F9 -> 0 | G17: =F17+G9 -> 0 | H17: =G17+H9 -> 0 | I17: =H17+I9 -> 0 | J17: =I17+J9 -> 0 | K17: =J17 -> 0
A18: =A10 -> Depositor 5 | F18: =$E10+F10 -> 0 | G18: =F18+G10 -> 0 | H18: =G18+H10 -> 0 | I18: =H18+I10 -> 0 | J18: =I18+J10 -> 0 | K18: =J18 -> 0
A19: Total closing balance | F19: =SUM(F14:F18) -> 1950 | G19: =SUM(G14:G18) -> 1950 | H19: =SUM(H14:H18) -> 1750 | I19: =SUM(I14:I18) -> 1800 | J19: =SUM(J14:J18) -> 1800 | K19: =SUM(K14:K18) -> 1800
A21: 3. Average balance for the quarter | F21: =Assumptions!F$10 -> Q4-2026 | G21: =Assumptions!G$10 -> Q1-2027 | H21: =Assumptions!H$10 -> Q2-2027 | I21: =Assumptions!I$10 -> Q3-2027 | J21: =Assumptions!J$10 -> Q4-2027 | K21: FY-2027 avg
A22: =A6 -> Ministry of Finance – term deposit | F22: =($E6+F14)/2 -> 1000 | G22: =(F14+G14)/2 -> 1000 | H22: =(G14+H14)/2 -> 900 | I22: =(H14+I14)/2 -> 800 | J22: =(I14+J14)/2 -> 800 | K22: =SUMPRODUCT(G22:J22,Assumptions!$G$13:$J$13)/SUM(Assumptions!$G$13:$J$13) -> 874.24658
A23: =A7 -> Govt entity X – floating deposit | F23: =($E7+F15)/2 -> 650 | G23: =(F15+G15)/2 -> 700 | H23: =(G15+H15)/2 -> 700 | I23: =(H15+I15)/2 -> 725 | J23: =(I15+J15)/2 -> 750 | K23: =SUMPRODUCT(G23:J23,Assumptions!$G$13:$J$13)/SUM(Assumptions!$G$13:$J$13) -> 718.90411
A24: =A8 -> Govt-related entity – call account | F24: =($E8+F16)/2 -> 250 | G24: =(F16+G16)/2 -> 250 | H24: =(G16+H16)/2 -> 250 | I24: =(H16+I16)/2 -> 250 | J24: =(I16+J16)/2 -> 250 | K24: =SUMPRODUCT(G24:J24,Assumptions!$G$13:$J$13)/SUM(Assumptions!$G$13:$J$13) -> 250
A25: =A9 -> Depositor 4 | F25: =($E9+F17)/2 -> 0 | G25: =(F17+G17)/2 -> 0 | H25: =(G17+H17)/2 -> 0 | I25: =(H17+I17)/2 -> 0 | J25: =(I17+J17)/2 -> 0 | K25: =SUMPRODUCT(G25:J25,Assumptions!$G$13:$J$13)/SUM(Assumptions!$G$13:$J$13) -> 0
A26: =A10 -> Depositor 5 | F26: =($E10+F18)/2 -> 0 | G26: =(F18+G18)/2 -> 0 | H26: =(G18+H18)/2 -> 0 | I26: =(H18+I18)/2 -> 0 | J26: =(I18+J18)/2 -> 0 | K26: =SUMPRODUCT(G26:J26,Assumptions!$G$13:$J$13)/SUM(Assumptions!$G$13:$J$13) -> 0
A27: Total average balance | F27: =SUM(F22:F26) -> 1900 | G27: =SUM(G22:G26) -> 1950 | H27: =SUM(H22:H26) -> 1850 | I27: =SUM(I22:I26) -> 1775 | J27: =SUM(J22:J26) -> 1800 | K27: =SUM(K22:K26) -> 1843.1507
A29: 4. Effective interest rate (annualised) | F29: =Assumptions!F$10 -> Q4-2026 | G29: =Assumptions!G$10 -> Q1-2027 | H29: =Assumptions!H$10 -> Q2-2027 | I29: =Assumptions!I$10 -> Q3-2027 | J29: =Assumptions!J$10 -> Q4-2027
A30: =A6 -> Ministry of Finance – term deposit | F30: =IF($B6="Fixed",$C6,Assumptions!F$14+$D6+Assumptions!$E$6) -> 0.039 | G30: =IF($B6="Fixed",$C6,Assumptions!G$14+$D6+Assumptions!$E$6) -> 0.039 | H30: =IF($B6="Fixed",$C6,Assumptions!H$14+$D6+Assumptions!$E$6) -> 0.039 | I30: =IF($B6="Fixed",$C6,Assumptions!I$14+$D6+Assumptions!$E$6) -> 0.039 | J30: =IF($B6="Fixed",$C6,Assumptions!J$14+$D6+Assumptions!$E$6) -> 0.039
A31: =A7 -> Govt entity X – floating deposit | F31: =IF($B7="Fixed",$C7,Assumptions!F$14+$D7+Assumptions!$E$6) -> 0.0365 | G31: =IF($B7="Fixed",$C7,Assumptions!G$14+$D7+Assumptions!$E$6) -> 0.035 | H31: =IF($B7="Fixed",$C7,Assumptions!H$14+$D7+Assumptions!$E$6) -> 0.0335 | I31: =IF($B7="Fixed",$C7,Assumptions!I$14+$D7+Assumptions!$E$6) -> 0.0325 | J31: =IF($B7="Fixed",$C7,Assumptions!J$14+$D7+Assumptions!$E$6) -> 0.0325
A32: =A8 -> Govt-related entity – call account | F32: =IF($B8="Fixed",$C8,Assumptions!F$14+$D8+Assumptions!$E$6) -> 0.005 | G32: =IF($B8="Fixed",$C8,Assumptions!G$14+$D8+Assumptions!$E$6) -> 0.005 | H32: =IF($B8="Fixed",$C8,Assumptions!H$14+$D8+Assumptions!$E$6) -> 0.005 | I32: =IF($B8="Fixed",$C8,Assumptions!I$14+$D8+Assumptions!$E$6) -> 0.005 | J32: =IF($B8="Fixed",$C8,Assumptions!J$14+$D8+Assumptions!$E$6) -> 0.005
A33: =A9 -> Depositor 4 | F33: =IF($B9="Fixed",$C9,Assumptions!F$14+$D9+Assumptions!$E$6) -> 0.039 | G33: =IF($B9="Fixed",$C9,Assumptions!G$14+$D9+Assumptions!$E$6) -> 0.0375 | H33: =IF($B9="Fixed",$C9,Assumptions!H$14+$D9+Assumptions!$E$6) -> 0.036 | I33: =IF($B9="Fixed",$C9,Assumptions!I$14+$D9+Assumptions!$E$6) -> 0.035 | J33: =IF($B9="Fixed",$C9,Assumptions!J$14+$D9+Assumptions!$E$6) -> 0.035
A34: =A10 -> Depositor 5 | F34: =IF($B10="Fixed",$C10,Assumptions!F$14+$D10+Assumptions!$E$6) -> 0.039 | G34: =IF($B10="Fixed",$C10,Assumptions!G$14+$D10+Assumptions!$E$6) -> 0.0375 | H34: =IF($B10="Fixed",$C10,Assumptions!H$14+$D10+Assumptions!$E$6) -> 0.036 | I34: =IF($B10="Fixed",$C10,Assumptions!I$14+$D10+Assumptions!$E$6) -> 0.035 | J34: =IF($B10="Fixed",$C10,Assumptions!J$14+$D10+Assumptions!$E$6) -> 0.035
A35: Weighted average rate | F35: =IFERROR(F43/F27*Assumptions!$E$5/Assumptions!F$13,0) -> 0.033671053 | G35: =IFERROR(G43/G27*Assumptions!$E$5/Assumptions!G$13,0) -> 0.033205128 | H35: =IFERROR(H43/H27*Assumptions!$E$5/Assumptions!H$13,0) -> 0.032324324 | I35: =IFERROR(I43/I27*Assumptions!$E$5/Assumptions!I$13,0) -> 0.031556338 | J35: =IFERROR(J43/J27*Assumptions!$E$5/Assumptions!J$13,0) -> 0.031569444 | K35: =IFERROR(K43/K27*Assumptions!$E$5/SUM(Assumptions!$G$13:$J$13),0) -> 0.032181865
A37: 5. Interest expense | F37: =Assumptions!F$10 -> Q4-2026 | G37: =Assumptions!G$10 -> Q1-2027 | H37: =Assumptions!H$10 -> Q2-2027 | I37: =Assumptions!I$10 -> Q3-2027 | J37: =Assumptions!J$10 -> Q4-2027 | K37: FY-2027
A38: =A6 -> Ministry of Finance – term deposit | F38: =F22*F30*Assumptions!F$13/Assumptions!$E$5 -> 9.9666667 | G38: =G22*G30*Assumptions!G$13/Assumptions!$E$5 -> 9.75 | H38: =H22*H30*Assumptions!H$13/Assumptions!$E$5 -> 8.8725 | I38: =I22*I30*Assumptions!I$13/Assumptions!$E$5 -> 7.9733333 | J38: =J22*J30*Assumptions!J$13/Assumptions!$E$5 -> 7.9733333 | K38: =SUM(G38:J38) -> 34.569167
A39: =A7 -> Govt entity X – floating deposit | F39: =F23*F31*Assumptions!F$13/Assumptions!$E$5 -> 6.0630556 | G39: =G23*G31*Assumptions!G$13/Assumptions!$E$5 -> 6.125 | H39: =H23*H31*Assumptions!H$13/Assumptions!$E$5 -> 5.9276389 | I39: =I23*I31*Assumptions!I$13/Assumptions!$E$5 -> 6.0215278 | J39: =J23*J31*Assumptions!J$13/Assumptions!$E$5 -> 6.2291667 | K39: =SUM(G39:J39) -> 24.303333
A40: =A8 -> Govt-related entity – call account | F40: =F24*F32*Assumptions!F$13/Assumptions!$E$5 -> 0.31944444 | G40: =G24*G32*Assumptions!G$13/Assumptions!$E$5 -> 0.3125 | H40: =H24*H32*Assumptions!H$13/Assumptions!$E$5 -> 0.31597222 | I40: =I24*I32*Assumptions!I$13/Assumptions!$E$5 -> 0.31944444 | J40: =J24*J32*Assumptions!J$13/Assumptions!$E$5 -> 0.31944444 | K40: =SUM(G40:J40) -> 1.2673611
A41: =A9 -> Depositor 4 | F41: =F25*F33*Assumptions!F$13/Assumptions!$E$5 -> 0 | G41: =G25*G33*Assumptions!G$13/Assumptions!$E$5 -> 0 | H41: =H25*H33*Assumptions!H$13/Assumptions!$E$5 -> 0 | I41: =I25*I33*Assumptions!I$13/Assumptions!$E$5 -> 0 | J41: =J25*J33*Assumptions!J$13/Assumptions!$E$5 -> 0 | K41: =SUM(G41:J41) -> 0
A42: =A10 -> Depositor 5 | F42: =F26*F34*Assumptions!F$13/Assumptions!$E$5 -> 0 | G42: =G26*G34*Assumptions!G$13/Assumptions!$E$5 -> 0 | H42: =H26*H34*Assumptions!H$13/Assumptions!$E$5 -> 0 | I42: =I26*I34*Assumptions!I$13/Assumptions!$E$5 -> 0 | J42: =J26*J34*Assumptions!J$13/Assumptions!$E$5 -> 0 | K42: =SUM(G42:J42) -> 0
A43: Total interest expense | F43: =SUM(F38:F42) -> 16.349167 | G43: =SUM(G38:G42) -> 16.1875 | H43: =SUM(H38:H42) -> 15.116111 | I43: =SUM(I38:I42) -> 14.314306 | J43: =SUM(J38:J42) -> 14.521944 | K43: =SUM(K38:K42) -> 60.139861
